setup.py
django_expirefield.egg-info/PKG-INFO
django_expirefield.egg-info/SOURCES.txt
django_expirefield.egg-info/dependency_links.txt
django_expirefield.egg-info/requires.txt
django_expirefield.egg-info/top_level.txt
expirefield/__init__.py
expirefield/fields.py
expirefield/management/__init__.py
expirefield/management/commands/__init__.py
expirefield/management/commands/expire.py