Metadata-Version: 1.1
Name: django-expirefield
Version: 0.0.2
Summary: ExpireField for django models that will remove fields at regular intervals
Home-page: https://github.com/malloc47/django-expirefield
Author: Jarrell Waggoner
Author-email: malloc47@gmail.com
License: LICENSE.txt
Download-URL: https://github.com/malloc47/expirefield/tarball/master#egg=expirefield-0.0.2
Platform: UNKNOWN
